faust_large_message_serializer/__init__.py
faust_large_message_serializer/config.py
faust_large_message_serializer/serializer.py
faust_large_message_serializer/blob_storage/__init__.py
faust_large_message_serializer/blob_storage/amazon_blob_storage.py
faust_large_message_serializer/blob_storage/azure_blob_storage.py
faust_large_message_serializer/blob_storage/blob_storage.py
faust_large_message_serializer/blob_storage/empty_blob.py
faust_large_message_serializer/clients/__init__.py
faust_large_message_serializer/clients/retrieving_client.py
faust_large_message_serializer/clients/storing_client.py
faust_large_message_serializer/utils/__init__.py
faust_large_message_serializer/utils/uri_parser.py
faust_large_message_serializer-2.0.1.dist-info/LICENSE
faust_large_message_serializer-2.0.1.dist-info/WHEEL
faust_large_message_serializer-2.0.1.dist-info/METADATA
faust_large_message_serializer-2.0.1.dist-info/RECORD
